{
    "width": 1024,
    "height": 576,
    "output_folder": "applications/pikachu/_output",
    "output_name": "1.png",
    "background": "applications/pikachu/background/background5.jpg",
    "font_path": "./fonts/Super Lobster.ttf",
    "sticker": [
        {
            "path": "applications/pikachu/stickers/28.png",
            "x": -20,
            "y": -10,
            "size": 400
        }
    ],
    "texts": [
        {
            "text": "Unlimited fun",
            "x": 80,
            "y": 350,
            "width": 600,
            "size": 50
        },
        {
            "text": "Vivid graphics",
            "x": 120,
            "y": 410,
            "width": 600,
            "size": 50
        },
        {
            "text": "Exciting adventures",
            "x": 10,
            "y": 470,
            "width": 600,
            "size": 50
        }
    ],
    "devices": [
        {
            "device_frame": "applications/pikachu/frame/frame_trimmed.png",
            "screenshot": "applications/pikachu/screen_shoots/1.png",
            "x": 350,
            "y": 0,
            "size": 800,
            "rotate": 15
        },
        {
            "device_frame": "applications/pikachu/frame/frame_trimmed.png",
            "screenshot": "applications/pikachu/screen_shoots/2.png",
            "x": 600,
            "y": 0,
            "size": 800,
            "rotate": 15
        }
    ]
}